mealieapi/__init__.py
mealieapi/auth.py
mealieapi/backup.py
mealieapi/client.py
mealieapi/const.py
mealieapi/errors.py
mealieapi/events.py
mealieapi/meals.py
mealieapi/migrations.py
mealieapi/misc.py
mealieapi/model.py
mealieapi/raw.py
mealieapi/recipes.py
mealieapi/settings.py
mealieapi/users.py
mealieapi-0.0.1.dist-info/METADATA
mealieapi-0.0.1.dist-info/LICENSE
mealieapi-0.0.1.dist-info/WHEEL
mealieapi-0.0.1.dist-info/RECORD
