Metadata-Version: 2.1
Name: mealieapi
Version: 0.0.1
Summary: Control your Mealie instance with python!
Home-page: https://github.com/GrandMoff100/MealieAPI
License: GPL-3.0-or-later
Author: GrandMoff100
Author-email: nlarsen23.student@gmail.com
Maintainer: GrandMoff100
Maintainer-email: nlarsen23.student@gmail.com
Requires-Python: >=3.7,<4.0
Classifier: License :: OSI Approved :: GNU General Public License v3 or later (GPLv3+)
Classifier: Programming Language :: Python :: 3
Classifier: Programming Language :: Python :: 3.7
Classifier: Programming Language :: Python :: 3.8
Classifier: Programming Language :: Python :: 3.9
Classifier: Programming Language :: Python :: 3.10
Classifier: Programming Language :: Python :: 3.11
Requires-Dist: aiohttp (>=3.8.1,<4.0.0)
Requires-Dist: pydantic (>=1.9.1,<2.0.0)
Requires-Dist: python-slugify (>=4.0.1,<5.0.0)
Project-URL: Documentation, https://github.com/GrandMoff100/MealieAPI/tree/master/README.md
Project-URL: Repository, https://github.com/GrandMoff100/MealieAPI
